odoo9_addon_project_stage_state-9.0.1.0.0-py2.7-nspkg.pth
odoo9_addon_project_stage_state-9.0.1.0.0.dist-info/DESCRIPTION.rst
odoo9_addon_project_stage_state-9.0.1.0.0.dist-info/METADATA
odoo9_addon_project_stage_state-9.0.1.0.0.dist-info/RECORD
odoo9_addon_project_stage_state-9.0.1.0.0.dist-info/WHEEL
odoo9_addon_project_stage_state-9.0.1.0.0.dist-info/metadata.json
odoo9_addon_project_stage_state-9.0.1.0.0.dist-info/namespace_packages.txt
odoo9_addon_project_stage_state-9.0.1.0.0.dist-info/top_level.txt
odoo_addons/project_stage_state/README.rst
odoo_addons/project_stage_state/__init__.py
odoo_addons/project_stage_state/__openerp__.py
odoo_addons/project_stage_state/i18n/ar.po
odoo_addons/project_stage_state/i18n/ca.po
odoo_addons/project_stage_state/i18n/de.po
odoo_addons/project_stage_state/i18n/el.po
odoo_addons/project_stage_state/i18n/es.po
odoo_addons/project_stage_state/i18n/es_CR.po
odoo_addons/project_stage_state/i18n/es_MX.po
odoo_addons/project_stage_state/i18n/es_VE.po
odoo_addons/project_stage_state/i18n/fi.po
odoo_addons/project_stage_state/i18n/fr.po
odoo_addons/project_stage_state/i18n/gl.po
odoo_addons/project_stage_state/i18n/hr.po
odoo_addons/project_stage_state/i18n/hu.po
odoo_addons/project_stage_state/i18n/it.po
odoo_addons/project_stage_state/i18n/ja.po
odoo_addons/project_stage_state/i18n/lt.po
odoo_addons/project_stage_state/i18n/lv.po
odoo_addons/project_stage_state/i18n/mk.po
odoo_addons/project_stage_state/i18n/mn.po
odoo_addons/project_stage_state/i18n/nl.po
odoo_addons/project_stage_state/i18n/pl.po
odoo_addons/project_stage_state/i18n/project_stage_state.pot
odoo_addons/project_stage_state/i18n/pt.po
odoo_addons/project_stage_state/i18n/pt_BR.po
odoo_addons/project_stage_state/i18n/pt_PT.po
odoo_addons/project_stage_state/i18n/ro.po
odoo_addons/project_stage_state/i18n/sl.po
odoo_addons/project_stage_state/i18n/sv.po
odoo_addons/project_stage_state/i18n/tr.po
odoo_addons/project_stage_state/i18n/zh_CN.po
odoo_addons/project_stage_state/models/__init__.py
odoo_addons/project_stage_state/models/project_task.py
odoo_addons/project_stage_state/static/description/icon.png
odoo_addons/project_stage_state/views/project_task_view.xml
