Metadata-Version: 2.0
Name: odoo9-addon-project-stage-state
Version: 9.0.1.0.0
Summary: Restore State attribute removed from Project Stages in 8.0
Home-page: https://github.com/OCA/project
Author: Daniel Reis, Odoo Community Association (OCA)
Author-email: support@odoo-community.org
License: AGPL-3
Platform: UNKNOWN
Classifier: Programming Language :: Python :: 2.7
Classifier: Framework :: Odoo
Classifier: License :: OSI Approved :: GNU Affero General Public License v3
Requires-Dist: odoo (<9.1a,>=9.0a)
